{
    "header": {
        "resultCode": 0,
        "resultMessage": "success",
        "isSuccessful": true
    },
    "totalItems": 25,
    "restaurants": [
        {
            "id": "string",
            "name": "고봉민김밥",
            "description": "김밥 존맛탱",
            "imgs": [
                {
                    "url": "string",
                    "description": "참치김밥",
                    "type": "MAIN"
                }
            ],
            "address": "부천시 어딘가",
            "location": {
                "lat": 111,
                "lng": 151
            },
            "webSiteUrl": "string",
            "phoneNumber": "000-0000-0000",
            "priceRange": 3,
            "rating": 5,
            "hours": {
                "hourType": "NORMAL",
                "open": 10,
                "close": 10
            },
            "categoryType": "KOREAN"
        }
    ]
}